[
  {
    "NAME_TABLE": "TABLE_GENERATE_0",
    "ROW_NUM": 1,
    "GENERAL_BOND_CODE": "IB1406-01",
    "GENERAL_BOND_NAME": "IB1406-01-TEST THU PHI",
    "GENERAL_BOND_PRICE": 152169,
    "INFO": "Số lượng trái phiếu còn lại",
    "NUM_MEMBER": "066",
    "NUM_IN": 1542,
    "NUM_OUT": 42,
    "NUM_TOTAL": 1584
  },
  {
    "NAME_TABLE": "TABLE_GENERATE_0",
    "ROW_NUM": 2,
    "GENERAL_BOND_CODE": "IB1406-01",
    "GENERAL_BOND_NAME": "IB1406-01-TEST THU PHI",
    "GENERAL_BOND_PRICE": 152169,
    "INFO": "Số lượng trái phiếu được quyền bán lại",
    "NUM_MEMBER": "066",
    "NUM_IN": 1542,
    "NUM_OUT": 42,
    "NUM_TOTAL": 1584
  },
  {
    "NAME_TABLE": "TABLE_GENERATE_0",
    "ROW_NUM": 3,
    "GENERAL_BOND_CODE": "IB1406-01",
    "GENERAL_BOND_NAME": "IB1406-01-TEST THU PHI",
    "GENERAL_BOND_PRICE": 152169,
    "INFO": "Số lượng trái phiếu đăng ký bán lại",
    "NUM_MEMBER": "066",
    "NUM_IN": 1542,
    "NUM_OUT": 42,
    "NUM_TOTAL": 1584
  },
  {
    "NAME_TABLE": "TABLE_GENERATE_0",
    "ROW_NUM": 4,
    "GENERAL_BOND_CODE": "IB1406-01",
    "GENERAL_BOND_NAME": "IB1406-01-TEST THU PHI",
    "GENERAL_BOND_PRICE": 152169,
    "INFO": "Số lượng trái phiếu sở hữu",
    "NUM_MEMBER": "066",
    "NUM_IN": 1542,
    "NUM_OUT": 42,
    "NUM_TOTAL": 1584
  }
]